optionchain_stream/__init__.py
optionchain_stream/instrument_file.py
optionchain_stream/option_chain.py
optionchain_stream/redis_instrument.py
optionchain_stream/websocket.py
optionchain_stream-0.6.dist-info/LICENSE
optionchain_stream-0.6.dist-info/METADATA
optionchain_stream-0.6.dist-info/WHEEL
optionchain_stream-0.6.dist-info/top_level.txt
optionchain_stream-0.6.dist-info/RECORD
