Metadata-Version: 2.1
Name: optionchain-stream
Version: 0.6
Summary: Python library for live streaming option chain using Kiteconnect Websocket
Home-page: https://github.com/ranjanrak/OptionChainStream
Author: Rakesh R
Author-email: rrrakesh265@gmail.com
License: MIT
Platform: UNKNOWN
Classifier: Programming Language :: Python :: 3
Classifier: License :: OSI Approved :: MIT License
Classifier: Topic :: Software Development :: Libraries
Requires-Dist: redis
